qaviton_ssh/__init__.py
qaviton_ssh-2019.10.18.22.29.29.465016.dist-info/LICENSE
qaviton_ssh-2019.10.18.22.29.29.465016.dist-info/METADATA
qaviton_ssh-2019.10.18.22.29.29.465016.dist-info/WHEEL
qaviton_ssh-2019.10.18.22.29.29.465016.dist-info/top_level.txt
qaviton_ssh-2019.10.18.22.29.29.465016.dist-info/RECORD
