Metadata-Version: 2.1
Name: qaviton-ssh
Version: 2019.10.18.22.29.29.465016
Summary: qaviton ssh
Home-page: https://github.com/qaviton/qaviton_ssh
Author: yehonadav
Author-email: yonadav.barilan@gmail.com
License: apache-2.0
Platform: UNKNOWN
Classifier: Programming Language :: Python :: 3.6
Requires-Dist: paramiko (>=2.6.0)
